typer_passwd/.vscode/settings.json
typer_passwd/__init__.py
typer_passwd/__main__.py
typer_passwd/main.py
typer_passwd-0.1.4.dist-info/entry_points.txt
typer_passwd-0.1.4.dist-info/WHEEL
typer_passwd-0.1.4.dist-info/METADATA
typer_passwd-0.1.4.dist-info/RECORD
