Metadata-Version: 2.1
Name: typer-passwd
Version: 0.1.4
Summary: Simple CLI app that generates random passwords.
Author: Mrnobody
Author-email: mrcartoonster@icloud.com
Requires-Python: >=3.8,<4.0
Classifier: Programming Language :: Python :: 3
Classifier: Programming Language :: Python :: 3.8
Requires-Dist: colorful (>=0.5.4,<0.6.0)
Requires-Dist: pyperclip (>=1.8.0,<2.0.0)
Requires-Dist: typer[all] (>=0.3.0,<0.4.0)
Requires-Dist: wasabi (>=0.7.1,<0.8.0)
Requires-Dist: yakutils (>=1.7.0,<2.0.0)
